odoo/addons/base_multicompany_reporting_currency/README.rst
odoo/addons/base_multicompany_reporting_currency/__init__.py
odoo/addons/base_multicompany_reporting_currency/__manifest__.py
odoo/addons/base_multicompany_reporting_currency/data/default_multicompany_reporting_currency.xml
odoo/addons/base_multicompany_reporting_currency/i18n/base_multicompany_reporting_currency.pot
odoo/addons/base_multicompany_reporting_currency/i18n/ca.po
odoo/addons/base_multicompany_reporting_currency/i18n/it.po
odoo/addons/base_multicompany_reporting_currency/models/__init__.py
odoo/addons/base_multicompany_reporting_currency/models/res_config_settings.py
odoo/addons/base_multicompany_reporting_currency/readme/CONTRIBUTORS.rst
odoo/addons/base_multicompany_reporting_currency/readme/DESCRIPTION.rst
odoo/addons/base_multicompany_reporting_currency/static/description/icon.png
odoo/addons/base_multicompany_reporting_currency/static/description/index.html
odoo/addons/base_multicompany_reporting_currency/views/res_config_settings_views.xml
odoo_addon_base_multicompany_reporting_currency-16.0.1.0.0.2.dist-info/METADATA
odoo_addon_base_multicompany_reporting_currency-16.0.1.0.0.2.dist-info/WHEEL
odoo_addon_base_multicompany_reporting_currency-16.0.1.0.0.2.dist-info/top_level.txt
odoo_addon_base_multicompany_reporting_currency-16.0.1.0.0.2.dist-info/RECORD
