Metadata-Version: 2.1
Name: odoo-addon-base_multicompany_reporting_currency
Version: 16.0.1.0.0.2
Summary: Adds the possibility to specify Multicompany Reporting Currency
Home-page: https://github.com/OCA/sale-reporting
Author: Camptocamp SA, Odoo Community Association (OCA)
Author-email: support@odoo-community.org
License: AGPL-3
Classifier: Programming Language :: Python
Classifier: Framework :: Odoo
Classifier: Framework :: Odoo :: 16.0
Classifier: License :: OSI Approved :: GNU Affero General Public License v3
Requires-Python: >=3.10
Requires-Dist: odoo<16.1dev,>=16.0a
